autowhat/__init__.py
autowhat/group_creator.py
autowhat/helper.py
autowhat/initializer.py
autowhat/sender.py
autowhat/spammer.py
autowhat-0.0.7.dist-info/METADATA
autowhat-0.0.7.dist-info/WHEEL
autowhat-0.0.7.dist-info/top_level.txt
autowhat-0.0.7.dist-info/RECORD
