Metadata-Version: 2.1
Name: autowhat
Version: 0.0.7
Summary: A Package which helps in easing your automations involving whatsapp
Home-page: UNKNOWN
Author: Giri
Author-email: <karnatisaivenkatagiri@gmail.com>
License: UNKNOWN
Keywords: python,first package
Platform: UNKNOWN
Classifier: Development Status :: 3 - Alpha
Classifier: Intended Audience :: Education
Classifier: Programming Language :: Python :: 3
Classifier: Operating System :: MacOS :: MacOS X
Classifier: Operating System :: Microsoft :: Windows
Requires-Dist: gTTS
Requires-Dist: Selenium
